odoo/addons/account_move_name_sequence/README.rst
odoo/addons/account_move_name_sequence/__init__.py
odoo/addons/account_move_name_sequence/__manifest__.py
odoo/addons/account_move_name_sequence/post_install.py
odoo/addons/account_move_name_sequence/demo/account_journal_demo.xml
odoo/addons/account_move_name_sequence/demo/ir_sequence_demo.xml
odoo/addons/account_move_name_sequence/i18n/account_move_name_sequence.pot
odoo/addons/account_move_name_sequence/i18n/es.po
odoo/addons/account_move_name_sequence/i18n/fr.po
odoo/addons/account_move_name_sequence/i18n/hr.po
odoo/addons/account_move_name_sequence/i18n/it.po
odoo/addons/account_move_name_sequence/i18n/sl.po
odoo/addons/account_move_name_sequence/models/__init__.py
odoo/addons/account_move_name_sequence/models/account_journal.py
odoo/addons/account_move_name_sequence/models/account_move.py
odoo/addons/account_move_name_sequence/models/ir_sequence.py
odoo/addons/account_move_name_sequence/readme/CONFIGURE.rst
odoo/addons/account_move_name_sequence/readme/CONTRIBUTORS.rst
odoo/addons/account_move_name_sequence/readme/DESCRIPTION.rst
odoo/addons/account_move_name_sequence/security/ir.model.access.csv
odoo/addons/account_move_name_sequence/static/description/icon.png
odoo/addons/account_move_name_sequence/static/description/index.html
odoo/addons/account_move_name_sequence/tests/__init__.py
odoo/addons/account_move_name_sequence/tests/test_account_incoming_supplier_invoice.py
odoo/addons/account_move_name_sequence/tests/test_account_move_name_seq.py
odoo/addons/account_move_name_sequence/tests/test_sequence_concurrency.py
odoo/addons/account_move_name_sequence/views/account_journal_views.xml
odoo/addons/account_move_name_sequence/views/account_move_views.xml
odoo14_addon_account_move_name_sequence-14.0.1.4.5.dist-info/METADATA
odoo14_addon_account_move_name_sequence-14.0.1.4.5.dist-info/WHEEL
odoo14_addon_account_move_name_sequence-14.0.1.4.5.dist-info/top_level.txt
odoo14_addon_account_move_name_sequence-14.0.1.4.5.dist-info/RECORD
